daraja_client/__init__.py
daraja_client/core.py
daraja_client/test.py
daraja_client/utils.py
daraja_client-0.1.2.dist-info/LICENSE
daraja_client-0.1.2.dist-info/METADATA
daraja_client-0.1.2.dist-info/WHEEL
daraja_client-0.1.2.dist-info/top_level.txt
daraja_client-0.1.2.dist-info/RECORD
