Metadata-Version: 2.1
Name: daraja_client
Version: 0.1.2
Summary: This python module provides a simple way to integrate the Safaricom MPESA Daraja 2.0 API into your Python projects. It is designed to handle common operations like generating access tokens, formatting phone numbers, and sending STK Push requests.
Home-page: https://github.com/anomalous254/daraja_client
Author: Peter Nyando
Author-email: peternyando2@gmail.com
Classifier: Programming Language :: Python :: 3
Classifier: License :: OSI Approved :: MIT License
Classifier: Operating System :: OS Independent
Requires-Python: >=3.7
License-File: LICENSE
Requires-Dist: certifi ==2024.8.30
Requires-Dist: charset-normalizer ==3.4.0
Requires-Dist: idna ==3.10
Requires-Dist: requests ==2.32.3
Requires-Dist: urllib3 ==2.2.3
Requires-Dist: python-decouple ==3.8
